{
  "student_id": "20250527_093521",
  "project_title": "Crazy Rich Asians",
  "timestamp": "2025-05-27T09:39:35.173735",
  "responses": {
    "q1": "Crazy Rich Asians",
    "q2": "flask, jinja, html, css, json, js, after effects, premiere, vfx, 2d and 3d animation, web design",
    "q3": "Many kids including myself are not financially literate, especially compared to migrant parents, we want to learn from them, be inspired, be guided, but also received specific and explicit advice how to grow our weath and future",
    "q4": "web design, coding, multimedia, game development, vfx, 2d and 3d animation",
    "q5": "i grew up hearing stories about my parents and grandparents, lots of my friends too, but we find it hard to relate it to what we have now, our entitlements and privelege"
  }
}